README.md
setup.py
dawetsql/__init__.py
dawetsql/completer.py
dawetsql/odbc_sql.py
dawetsql/utils.py
dawetsql/widgets.py
ipython_dawet_sql.egg-info/PKG-INFO
ipython_dawet_sql.egg-info/SOURCES.txt
ipython_dawet_sql.egg-info/dependency_links.txt
ipython_dawet_sql.egg-info/requires.txt
ipython_dawet_sql.egg-info/top_level.txt