Metadata-Version: 2.1
Name: ipython-dawet-sql
Version: 0.1b10
Summary: Ipython ODBC SQL Magic for Dawet
Home-page: https://gitlab.com/wakataw/ipython-dawet-sql
Author: Agung Pratama
Author-email: agungpratama1001@gmail.com
License: MIT
Platform: UNKNOWN
Classifier: Development Status :: 4 - Beta
Classifier: Intended Audience :: Developers
Classifier: Topic :: Internet :: WWW/HTTP :: Dynamic Content :: CGI Tools/Libraries
Classifier: Topic :: Software Development :: Libraries :: Python Modules
Classifier: Topic :: Utilities
Classifier: Natural Language :: English
Classifier: Natural Language :: Indonesian
Classifier: Operating System :: OS Independent
Classifier: Programming Language :: Python :: 3.5
Classifier: License :: OSI Approved :: MIT License
Requires-Python: >=3.5
